GymBuddyApp/README.md
GymBuddyApp/manage.py
GymBuddyApp/requirements.txt
GymBuddyApp/activityLibrary/__init__.py
GymBuddyApp/activityLibrary/admin.py
GymBuddyApp/activityLibrary/apps.py
GymBuddyApp/activityLibrary/forms.py
GymBuddyApp/activityLibrary/models.py
GymBuddyApp/activityLibrary/tests.py
GymBuddyApp/activityLibrary/views.py
GymBuddyApp/activityLibrary/migrations/0001_initial.py
GymBuddyApp/activityLibrary/migrations/0002_auto_20201013_1315.py
GymBuddyApp/activityLibrary/migrations/0003_recipe_ingredients.py
GymBuddyApp/activityLibrary/migrations/0004_auto_20201013_2120.py
GymBuddyApp/activityLibrary/migrations/0004_auto_20201014_1327.py
GymBuddyApp/activityLibrary/migrations/0005_merge_20201015_0456.py
GymBuddyApp/activityLibrary/migrations/0006_auto_20201017_2044.py
GymBuddyApp/activityLibrary/migrations/0007_recipe_category.py
GymBuddyApp/activityLibrary/migrations/0008_auto_20201019_2116.py
GymBuddyApp/activityLibrary/migrations/__init__.py
GymBuddyApp/activityLibrary/templates/activityLibrary/search.html
GymBuddyApp/gymBuddyApp/Exercises.json
GymBuddyApp/gymBuddyApp/__init__.py
GymBuddyApp/gymBuddyApp/asgi.py
GymBuddyApp/gymBuddyApp/settings.py
GymBuddyApp/gymBuddyApp/urls.py
GymBuddyApp/gymBuddyApp/wsgi.py
GymBuddyApp/pages/__init__.py
GymBuddyApp/pages/admin.py
GymBuddyApp/pages/apps.py
GymBuddyApp/pages/models.py
GymBuddyApp/pages/tests.py
GymBuddyApp/pages/urls.py
GymBuddyApp/pages/views.py
GymBuddyApp/pages/migrations/__init__.py
GymBuddyApp/pages/static/pages/main.css
GymBuddyApp/pages/templates/pages/base.html
GymBuddyApp/pages/templates/pages/home.html
GymBuddyApp/static/Source/Magnific-Popup-master.zip
GymBuddyApp/static/Source/OwlCarousel2-2.3.4.zip
GymBuddyApp/static/Source/SlickNav-master.zip
GymBuddyApp/static/Source/bootstrap-4.4.1-dist.zip
GymBuddyApp/static/Source/font-awesome-4.7.0.zip
GymBuddyApp/static/Source/sass.zip
GymBuddyApp/static/css/style.css
GymBuddyApp/static/img/Macro-Graphic.png
GymBuddyApp/static/img/exercise-filler.jpg
GymBuddyApp-1.0.4.dist-info/METADATA
GymBuddyApp-1.0.4.dist-info/WHEEL
GymBuddyApp-1.0.4.dist-info/entry_points.txt
GymBuddyApp-1.0.4.dist-info/top_level.txt
GymBuddyApp-1.0.4.dist-info/RECORD
