Metadata-Version: 2.1
Name: GymBuddyApp
Version: 1.0.4
Summary: UNKNOWN
Home-page: https://github.com/CTKogstrom/GymBuddyApp
License: UNKNOWN
Platform: UNKNOWN
Requires-Python: >=3.6
Requires-Dist: Django (==3.1.2)
Requires-Dist: Pillow (==7.2.0)
Requires-Dist: asgiref (==3.2.10)
Requires-Dist: certifi (==2020.6.20)
Requires-Dist: cycler (==0.10.0)
Requires-Dist: django-crispy-forms (==1.9.2)
Requires-Dist: kiwisolver (==1.2.0)
Requires-Dist: matplotlib (==3.3.2)
Requires-Dist: numpy (==1.19.2)
Requires-Dist: pyparsing (==2.4.7)
Requires-Dist: python-dateutil (==2.8.1)
Requires-Dist: pytz (==2020.1)
Requires-Dist: six (==1.15.0)
Requires-Dist: sqlparse (==0.3.1)
Requires-Dist: testresources (==2.0.1)
